camera_service/__init__.py
camera_service/cam_capture.py
camera_service/constants.py
camera_service/data/frames.py
camera_service/generate_code.py
camera_service/helpers/poetry_install.py
camera_service/modules/modules_list.py
camera_service/modules/modules_processing.py
camera_service/utils/get_local_ip.py
camera_service/utils/get_modules_from_toml.py
camera_service-0.1.0.dist-info/entry_points.txt
camera_service-0.1.0.dist-info/METADATA
camera_service-0.1.0.dist-info/WHEEL
camera_service-0.1.0.dist-info/RECORD
