Metadata-Version: 2.1
Name: camera-service
Version: 0.1.0
Summary: 
Author: Your Name
Author-email: you@example.com
Requires-Python: >=3.12,<4.0
Classifier: Programming Language :: Python :: 3
Classifier: Programming Language :: Python :: 3.12
Requires-Dist: aiohttp (>=3.9.5,<4.0.0)
Requires-Dist: aiortc (>=1.8.0,<2.0.0)
Requires-Dist: flask (>=3.0.3,<4.0.0)
Requires-Dist: grpcio (>=1.63.0,<2.0.0)
Requires-Dist: grpcio-tools (>=1.63.0,<2.0.0)
Requires-Dist: opencv-python (>=4.9.0.80,<5.0.0.0)
Requires-Dist: protobuf (>=5.26.1,<6.0.0)
Requires-Dist: requests (==2.31.0)
Requires-Dist: starlette (>=0.37.2,<0.38.0)
Requires-Dist: toml (>=0.10.2,<0.11.0)
Requires-Dist: twirp (>=0.0.7,<0.0.8)
Requires-Dist: uvicorn (>=0.29.0,<0.30.0)
